geetak.py
geetak-0.2.3.dist-info/LICENCE
geetak-0.2.3.dist-info/METADATA
geetak-0.2.3.dist-info/WHEEL
geetak-0.2.3.dist-info/entry_points.txt
geetak-0.2.3.dist-info/RECORD
