Metadata-Version: 2.1
Name: geetak
Version: 0.2.3
Summary: This is a CLI for controlling GeeTak device
License: MIT
Author: muflih
Author-email: nurfaizimuflih10@gmail.com
Requires-Python: >=3.12,<4.0
Classifier: License :: OSI Approved :: MIT License
Classifier: Programming Language :: Python :: 3
Classifier: Programming Language :: Python :: 3.12
Classifier: Programming Language :: Python :: 3.13
Requires-Dist: click (>=8.1.8,<9.0.0)
Requires-Dist: hidapi (>=0.14.0.post4,<0.15.0)
Requires-Dist: ntplib (>=0.4.0,<0.5.0)
Requires-Dist: pywinusb (>=0.4,<0.5) ; sys_platform == "win32"
Requires-Dist: rich (>=13.9.4,<14.0.0)
Requires-Dist: rich-click (>=1.8.5,<2.0.0)
